umapy/__init__.py
umapy/_helpers.py
umapy/client.py
umapy/Exceptions/__init__.py
umapy/Exceptions/api_errors.py
umapy-1.0.0.dist-info/LICENSE
umapy-1.0.0.dist-info/METADATA
umapy-1.0.0.dist-info/WHEEL
umapy-1.0.0.dist-info/top_level.txt
umapy-1.0.0.dist-info/RECORD
