Metadata-Version: 2.1
Name: umapy
Version: 1.0.0
Summary: A python wrapper for UMA API
Home-page: https://github.com/Rexians/umapy
Author: Rexians
Author-email: admin@rexiansteam.tk
License: MIT
Project-URL: Bug Tracker, https://github.com/Rexians/umapy/issues
Keywords: uma,mcoc,umapy,api,wrapper
Classifier: Programming Language :: Python :: 3
Classifier: License :: OSI Approved :: MIT License
Classifier: Operating System :: OS Independent
Requires-Python: >=3.6
License-File: LICENSE
Requires-Dist: requests
